symmetricfields/__init__.py
symmetricfields/apps.py
symmetricfields/crypters.py
symmetricfields/exceptions.py
symmetricfields/fields.py
symmetricfields/mixins.py
symmetricfields/values.py
django_symmetric_fields-0.0.9.dist-info/LICENSE.txt
django_symmetric_fields-0.0.9.dist-info/METADATA
django_symmetric_fields-0.0.9.dist-info/WHEEL
django_symmetric_fields-0.0.9.dist-info/top_level.txt
django_symmetric_fields-0.0.9.dist-info/RECORD
