Metadata-Version: 2.1
Name: django-symmetric-fields
Version: 0.0.9
Summary: Symmetric encryption for model fields in Django
Home-page: https://github.com/Szczaleg/django-symmetric-fields
Author: Szczaleg
Classifier: Programming Language :: Python :: 3
Classifier: License :: OSI Approved :: MIT License
Classifier: Operating System :: OS Independent
Requires-Python: >=3.7
License-File: LICENSE.txt
Requires-Dist: cryptography
